audio_data_pytorch/__init__.py
audio_data_pytorch/utils.py
audio_data_pytorch/datasets/__init__.py
audio_data_pytorch/datasets/audio_web_dataset.py
audio_data_pytorch/datasets/audio_web_dataset_preprocessing.py
audio_data_pytorch/datasets/clotho_dataset.py
audio_data_pytorch/datasets/common_voice_dataset.py
audio_data_pytorch/datasets/libri_speech_dataset.py
audio_data_pytorch/datasets/lj_speech_dataset.py
audio_data_pytorch/datasets/meta_dataset.py
audio_data_pytorch/datasets/wav_dataset.py
audio_data_pytorch/datasets/youtube_dataset.py
audio_data_pytorch/transforms/__init__.py
audio_data_pytorch/transforms/all.py
audio_data_pytorch/transforms/crop.py
audio_data_pytorch/transforms/loudness.py
audio_data_pytorch/transforms/mono.py
audio_data_pytorch/transforms/randomcrop.py
audio_data_pytorch/transforms/resample.py
audio_data_pytorch/transforms/scale.py
audio_data_pytorch/transforms/stereo.py
audio_data_pytorch-0.0.19.dist-info/LICENSE
audio_data_pytorch-0.0.19.dist-info/METADATA
audio_data_pytorch-0.0.19.dist-info/WHEEL
audio_data_pytorch-0.0.19.dist-info/top_level.txt
audio_data_pytorch-0.0.19.dist-info/RECORD
