Metadata-Version: 2.1
Name: audio-data-pytorch
Version: 0.0.19
Summary: Audio Data - PyTorch
Home-page: https://github.com/archinetai/audio-data-pytorch
Author: Flavio Schneider
Author-email: archinetai@protonmail.com
License: MIT
Keywords: artificial intelligence,deep learning,audio dataset
Classifier: Development Status :: 4 - Beta
Classifier: Intended Audience :: Developers
Classifier: Topic :: Scientific/Engineering :: Artificial Intelligence
Classifier: License :: OSI Approved :: MIT License
Classifier: Programming Language :: Python :: 3.6
License-File: LICENSE
Requires-Dist: torch (>=1.6)
Requires-Dist: torchaudio (>=0.10.0)
Requires-Dist: data-science-types (>=0.2)
Requires-Dist: requests
Requires-Dist: tqdm
Requires-Dist: aiohttp
Requires-Dist: webdataset
Requires-Dist: tinytag
Requires-Dist: bidict
Requires-Dist: pandas
Requires-Dist: yt-dlp
Requires-Dist: scipy
Requires-Dist: numpy
